ultra_chain_api/__init__.py
ultra_chain_api/api/api.py
ultra_chain_api/interfaces/abi_response.py
ultra_chain_api/interfaces/account_response.py
ultra_chain_api/interfaces/block_response.py
ultra_chain_api/interfaces/chain_info_response.py
ultra_chain_api/interfaces/code_response.py
ultra_chain_api/interfaces/factory_group_response.py
ultra_chain_api/interfaces/factory_response.py
ultra_chain_api/interfaces/producer_response.py
ultra_chain_api/interfaces/table_scope.py
ultra_chain_api/interfaces/transaction_response.py
ultra_chain_api/interfaces/uniq.py
ultra_chain_api-0.2.0.dist-info/METADATA
ultra_chain_api-0.2.0.dist-info/WHEEL
ultra_chain_api-0.2.0.dist-info/top_level.txt
ultra_chain_api-0.2.0.dist-info/RECORD
