Metadata-Version: 2.4
Name: ultra-chain-api
Version: 0.2.0
Summary: UltraChainAPI Python Client
Author-email: Hugo Chapon <chapon.hugo95@gmail.com>
Requires-Python: >=3.12
Requires-Dist: pydantic>=2.11.3
Requires-Dist: requests>=2.32.3
